dash_utils/__init__.py
dash_utils/dash_api/__init__.py
dash_utils/public_url/__init__.py
dash_utils-0.0.2.dist-info/METADATA
dash_utils-0.0.2.dist-info/WHEEL
dash_utils-0.0.2.dist-info/top_level.txt
dash_utils-0.0.2.dist-info/RECORD
