Metadata-Version: 2.1
Name: dash-utils
Version: 0.0.2
Summary: Utilities for Orenda serverless.
Home-page: https://github.com/andrewdircks/dash-utils
Author: Andrew Dircks
Author-email: andrew@orenda.group
License: UNKNOWN
Platform: UNKNOWN
Classifier: Programming Language :: Python :: 3
Classifier: Operating System :: OS Independent
Requires-Python: >=3.7
